onedrive_skill/__init__.py
onedrive_skill/onedrive_client.py
onedrive_skill-0.1.1.dist-info/LICENSE
onedrive_skill-0.1.1.dist-info/METADATA
onedrive_skill-0.1.1.dist-info/WHEEL
onedrive_skill-0.1.1.dist-info/top_level.txt
onedrive_skill-0.1.1.dist-info/RECORD
