Metadata-Version: 2.1
Name: onedrive-skill
Version: 0.1.1
Summary: A Python skill for connecting to Microsoft OneDrive via Graph API
Home-page: https://github.com/lucapaone76/onedrive-connect
Author: lucapaone76
Author-email: lucapaone@gmail.com
License: MIT
Project-URL: Homepage, https://github.com/lucapaone76/onedrive-connect
Project-URL: Repository, https://github.com/lucapaone76/onedrive-connect
Project-URL: Issues, https://github.com/lucapaone76/onedrive-connect/issues
Keywords: onedrive,microsoft,graph-api,llm,skill
Platform: UNKNOWN
Classifier: Development Status :: 3 - Alpha
Classifier: Intended Audience :: Developers
Classifier: License :: OSI Approved :: MIT License
Classifier: Programming Language :: Python :: 3
Classifier: Programming Language :: Python :: 3.8
Classifier: Programming Language :: Python :: 3.9
Classifier: Programming Language :: Python :: 3.10
Classifier: Programming Language :: Python :: 3.11
Classifier: Programming Language :: Python :: 3.12
Requires-Python: >=3.8
Requires-Dist: requests >=2.31.0
Provides-Extra: auth
Requires-Dist: msal >=1.20.0 ; extra == 'auth'
Requires-Dist: python-dotenv >=1.0.0 ; extra == 'auth'
Provides-Extra: dev
Requires-Dist: pytest >=7.0.0 ; extra == 'dev'
Requires-Dist: pytest-cov >=4.0.0 ; extra == 'dev'
Requires-Dist: black >=23.0.0 ; extra == 'dev'
Requires-Dist: ruff >=0.1.0 ; extra == 'dev'
